finopsmetrics/__init__.py
finopsmetrics/dashboard/__init__.py
finopsmetrics/dashboard/auth_middleware.py
finopsmetrics/dashboard/cfo_dashboard.py
finopsmetrics/dashboard/coo_dashboard.py
finopsmetrics/dashboard/dashboard_router.py
finopsmetrics/dashboard/finance_analyst_dashboard.py
finopsmetrics/dashboard/iam_cli.py
finopsmetrics/dashboard/iam_config.yaml
finopsmetrics/dashboard/iam_config_loader.py
finopsmetrics/dashboard/iam_system.py
finopsmetrics/dashboard/infrastructure_leader_dashboard.py
finopsmetrics/dashboard/model_cost_dashboard.py
finopsmetrics/dashboard/recommendations_dashboard.py
finopsmetrics/dashboard/__pycache__/__init__.cpython-313.pyc
finopsmetrics/dashboard/__pycache__/cfo_dashboard.cpython-313.pyc
finopsmetrics/dashboard/__pycache__/coo_dashboard.cpython-313.pyc
finopsmetrics/dashboard/__pycache__/dashboard_router.cpython-313.pyc
finopsmetrics/dashboard/__pycache__/finance_analyst_dashboard.cpython-313.pyc
finopsmetrics/dashboard/__pycache__/iam_config_loader.cpython-313.pyc
finopsmetrics/dashboard/__pycache__/iam_system.cpython-313.pyc
finopsmetrics/dashboard/__pycache__/infrastructure_leader_dashboard.cpython-313.pyc
finopsmetrics/dashboard/__pycache__/model_cost_dashboard.cpython-313.pyc
finopsmetrics/webui/__init__.py
finopsmetrics/webui/server.py
finopsmetrics/webui/__pycache__/__init__.cpython-313.pyc
finopsmetrics/webui/__pycache__/server.cpython-313.pyc
finopsmetrics/webui/templates/base.html
finopsmetrics/webui/templates/cfo_dashboard.html
finopsmetrics/webui/templates/coo_dashboard.html
finopsmetrics/webui/templates/index.html
finopsmetrics/webui/templates/infrastructure_dashboard.html
finopsmetrics_dashboard-0.3.1.dist-info/licenses/LICENSE
finopsmetrics_dashboard-0.3.1.dist-info/METADATA
finopsmetrics_dashboard-0.3.1.dist-info/WHEEL
finopsmetrics_dashboard-0.3.1.dist-info/entry_points.txt
finopsmetrics_dashboard-0.3.1.dist-info/top_level.txt
finopsmetrics_dashboard-0.3.1.dist-info/RECORD
