Metadata-Version: 2.4
Name: finopsmetrics-dashboard
Version: 0.3.1
Summary: FinOpsMetrics Dashboard - Web UI for FinOps Cost Monitoring & Analytics
Author-email: FinOpsMetrics <durai@infinidatum.net>
Maintainer-email: FinOpsMetrics <durai@infinidatum.net>
License: Proprietary
Project-URL: Homepage, https://github.com/rdmurugan/finopsmetrics-dashboard
Project-URL: Documentation, https://finopsmetrics.readthedocs.io/dashboard
Project-URL: Repository, https://github.com/rdmurugan/finopsmetrics-dashboard
Keywords: finops,dashboard,web-ui,monitoring,visualization,iam,rbac,real-time,websocket
Classifier: Development Status :: 4 - Beta
Classifier: Intended Audience :: Developers
Classifier: Intended Audience :: System Administrators
Classifier: Intended Audience :: Financial and Insurance Industry
Classifier: Topic :: System :: Monitoring
Classifier: Topic :: Office/Business :: Financial
Classifier: Framework :: Flask
Classifier: License :: Other/Proprietary License
Classifier: Programming Language :: Python :: 3
Classifier: Programming Language :: Python :: 3.8
Classifier: Programming Language :: Python :: 3.9
Classifier: Programming Language :: Python :: 3.10
Classifier: Programming Language :: Python :: 3.11
Classifier: Programming Language :: Python :: 3.12
Classifier: Operating System :: OS Independent
Requires-Python: >=3.8
License-File: LICENSE
Requires-Dist: finopsmetrics>=0.3.0
Requires-Dist: flask>=2.0.0
Requires-Dist: flask-socketio>=5.3.0
Requires-Dist: flask-cors>=4.0.0
Requires-Dist: eventlet>=0.33.0
Requires-Dist: pyyaml>=6.0
Provides-Extra: enterprise
Requires-Dist: finopsmetrics-enterprise>=0.3.0; extra == "enterprise"
Provides-Extra: dev
Requires-Dist: pytest>=7.0.0; extra == "dev"
Requires-Dist: pytest-cov>=4.0.0; extra == "dev"
Requires-Dist: black>=23.0.0; extra == "dev"
Requires-Dist: ruff>=0.1.0; extra == "dev"
Dynamic: license-file
